jupyterhub_share_link/__init__.py
jupyterhub_share_link/_version.py
jupyterhub_share_link/generate_keys.py
jupyterhub_share_link/launcher.py
jupyterhub_share_link/run.py
jupyterhub_share_link/tests/__init__.py
jupyterhub_share_link/tests/conftest.py
jupyterhub_share_link/tests/test_examples.py
jupyterhub_share_link-0.1.1.dist-info/METADATA
jupyterhub_share_link-0.1.1.dist-info/RECORD
jupyterhub_share_link-0.1.1.dist-info/WHEEL
jupyterhub_share_link-0.1.1.dist-info/entry_points.txt
jupyterhub_share_link-0.1.1.dist-info/top_level.txt
