Metadata-Version: 2.1
Name: jupyterhub-share-link
Version: 0.1.1
Summary: Make shareable links to notebooks.
Home-page: https://github.com/danielballan/jupyterhub-share-link
Author: JupyterHub Share Link Contributors
Author-email: dallan@bnl.gov
License: BSD (3-clause)
Platform: UNKNOWN
Classifier: Development Status :: 2 - Pre-Alpha
Classifier: Natural Language :: English
Classifier: Programming Language :: Python :: 3
Requires-Python: >=3.6
Requires-Dist: cryptography
Requires-Dist: jupyterhub
Requires-Dist: pyjwt
Requires-Dist: tornado
Requires-Dist: traitlets
